riptide/__init__.py
riptide/py.typed
riptide/util.py
riptide/assets/blank_project_config.yml
riptide/assets/blank_user_config.yml
riptide/config/__init__.py
riptide/config/errors.py
riptide/config/files.py
riptide/config/hosts.py
riptide/config/loader.py
riptide/config/repositories.py
riptide/config/command/__init__.py
riptide/config/command/in_service.py
riptide/config/document/__init__.py
riptide/config/document/app.py
riptide/config/document/command.py
riptide/config/document/common_service_command.py
riptide/config/document/config.py
riptide/config/document/hook.py
riptide/config/document/project.py
riptide/config/document/service.py
riptide/config/service/__init__.py
riptide/config/service/config_files.py
riptide/config/service/config_files_helper_functions.py
riptide/config/service/logging.py
riptide/config/service/ports.py
riptide/config/service/volumes.py
riptide/db/__init__.py
riptide/db/environments.py
riptide/db/driver/__init__.py
riptide/db/driver/abstract.py
riptide/db/driver/db_driver_for_service.py
riptide/db/impl/__init__.py
riptide/db/impl/data_directory.py
riptide/db/impl/named_volume.py
riptide/engine/__init__.py
riptide/engine/abstract.py
riptide/engine/error.py
riptide/engine/loader.py
riptide/engine/project_start_ctx.py
riptide/engine/results.py
riptide/engine/status.py
riptide/hook/__init__.py
riptide/hook/additional_volumes.py
riptide/hook/cli.py
riptide/hook/event.py
riptide/hook/manager.py
riptide/lib/__init__.py
riptide/lib/dict_merge.py
riptide/lib/cross_platform/__init__.py
riptide/lib/cross_platform/cppath.py
riptide/lib/cross_platform/cppty.py
riptide/lib/cross_platform/cpuser.py
riptide/plugin/__init__.py
riptide/plugin/abstract.py
riptide/plugin/loader.py
riptide/tests/__init__.py
riptide/tests/configcrunch_test_utils.py
riptide/tests/helpers.py
riptide/tests/stubs.py
riptide/tests/fixtures/app/integration_app.yml
riptide/tests/fixtures/app/invalid_no_name.yml
riptide/tests/fixtures/app/valid.yml
riptide_lib-0.10.1.dist-info/licenses/LICENSE
riptide_lib-0.10.1.dist-info/METADATA
riptide_lib-0.10.1.dist-info/WHEEL
riptide_lib-0.10.1.dist-info/top_level.txt
riptide_lib-0.10.1.dist-info/RECORD
