Metadata-Version: 2.4
Name: riptide-lib
Version: 0.10.1
Summary: Tool to manage development environments for web applications using containers - Library Package
Author-email: Marco Köpcke <hello@capypara.de>
License-Expression: MIT
Project-URL: Repository, https://github.com/theCapypara/riptide-lib
Project-URL: Documentation, https://riptide-docs.readthedocs.io
Classifier: Development Status :: 4 - Beta
Classifier: Programming Language :: Python
Classifier: Intended Audience :: Developers
Classifier: Programming Language :: Python :: 3.11
Classifier: Programming Language :: Python :: 3.12
Classifier: Programming Language :: Python :: 3.13
Classifier: Programming Language :: Python :: 3.14
Requires-Python: >=3.11
License-File: LICENSE
Requires-Dist: configcrunch>=2.1.0
Requires-Dist: schema>=0.7
Requires-Dist: pyyaml>=6.0
Requires-Dist: appdirs>=1.4
Requires-Dist: janus>=2.0
Requires-Dist: psutil>=7.0
Requires-Dist: GitPython>=3.1
Requires-Dist: pywinpty>=2.0; sys_platform == "win32"
Requires-Dist: python-hosts>=1.0
Requires-Dist: python-dotenv>=1.1.0
Dynamic: license-file
